{"kind":"symbol","abstract":[{"text":"Identifies source of ","type":"text"},{"type":"reference","isActive":true,"identifier":"doc:\/\/com.dxfeed.DXFeedFramework\/documentation\/DXFeedFramework\/Order"},{"type":"text","text":", "},{"type":"reference","identifier":"doc:\/\/com.dxfeed.DXFeedFramework\/documentation\/DXFeedFramework\/AnalyticOrder","isActive":true},{"type":"text","text":", OtcMarketsOrder and "},{"type":"reference","isActive":true,"identifier":"doc:\/\/com.dxfeed.DXFeedFramework\/documentation\/DXFeedFramework\/SpreadOrder"},{"type":"text","text":" events."}],"topicSections":[{"identifiers":["doc:\/\/com.dxfeed.DXFeedFramework\/documentation\/DXFeedFramework\/OrderSource\/isFullOrderBook()","doc:\/\/com.dxfeed.DXFeedFramework\/documentation\/DXFeedFramework\/OrderSource\/isPublishable(eventType:)"],"title":"Instance Methods"},{"identifiers":["doc:\/\/com.dxfeed.DXFeedFramework\/documentation\/DXFeedFramework\/OrderSource\/ABE","doc:\/\/com.dxfeed.DXFeedFramework\/documentation\/DXFeedFramework\/OrderSource\/ARCA-2h2y5","doc:\/\/com.dxfeed.DXFeedFramework\/documentation\/DXFeedFramework\/OrderSource\/BATE","doc:\/\/com.dxfeed.DXFeedFramework\/documentation\/DXFeedFramework\/OrderSource\/BI20","doc:\/\/com.dxfeed.DXFeedFramework\/documentation\/DXFeedFramework\/OrderSource\/BXTR","doc:\/\/com.dxfeed.DXFeedFramework\/documentation\/DXFeedFramework\/OrderSource\/BYX","doc:\/\/com.dxfeed.DXFeedFramework\/documentation\/DXFeedFramework\/OrderSource\/BZX-1fl38","doc:\/\/com.dxfeed.DXFeedFramework\/documentation\/DXFeedFramework\/OrderSource\/C2OX","doc:\/\/com.dxfeed.DXFeedFramework\/documentation\/DXFeedFramework\/OrderSource\/CEDX-8i4o9","doc:\/\/com.dxfeed.DXFeedFramework\/documentation\/DXFeedFramework\/OrderSource\/CEUX","doc:\/\/com.dxfeed.DXFeedFramework\/documentation\/DXFeedFramework\/OrderSource\/CFE","doc:\/\/com.dxfeed.DXFeedFramework\/documentation\/DXFeedFramework\/OrderSource\/CHIX","doc:\/\/com.dxfeed.DXFeedFramework\/documentation\/DXFeedFramework\/OrderSource\/DEA","doc:\/\/com.dxfeed.DXFeedFramework\/documentation\/DXFeedFramework\/OrderSource\/DEX-8eswp","doc:\/\/com.dxfeed.DXFeedFramework\/documentation\/DXFeedFramework\/OrderSource\/ERIS","doc:\/\/com.dxfeed.DXFeedFramework\/documentation\/DXFeedFramework\/OrderSource\/ESPD","doc:\/\/com.dxfeed.DXFeedFramework\/documentation\/DXFeedFramework\/OrderSource\/FAIR","doc:\/\/com.dxfeed.DXFeedFramework\/documentation\/DXFeedFramework\/OrderSource\/GLBX-8ulae","doc:\/\/com.dxfeed.DXFeedFramework\/documentation\/DXFeedFramework\/OrderSource\/ICE","doc:\/\/com.dxfeed.DXFeedFramework\/documentation\/DXFeedFramework\/OrderSource\/ISE","doc:\/\/com.dxfeed.DXFeedFramework\/documentation\/DXFeedFramework\/OrderSource\/IST","doc:\/\/com.dxfeed.DXFeedFramework\/documentation\/DXFeedFramework\/OrderSource\/MEMX-8i7t3","doc:\/\/com.dxfeed.DXFeedFramework\/documentation\/DXFeedFramework\/OrderSource\/NFX","doc:\/\/com.dxfeed.DXFeedFramework\/documentation\/DXFeedFramework\/OrderSource\/NTV-773uf","doc:\/\/com.dxfeed.DXFeedFramework\/documentation\/DXFeedFramework\/OrderSource\/OCEA","doc:\/\/com.dxfeed.DXFeedFramework\/documentation\/DXFeedFramework\/OrderSource\/SMFE-2xqm","doc:\/\/com.dxfeed.DXFeedFramework\/documentation\/DXFeedFramework\/OrderSource\/XEUR-fa6f","doc:\/\/com.dxfeed.DXFeedFramework\/documentation\/DXFeedFramework\/OrderSource\/XNFI","doc:\/\/com.dxfeed.DXFeedFramework\/documentation\/DXFeedFramework\/OrderSource\/agregateAsk","doc:\/\/com.dxfeed.DXFeedFramework\/documentation\/DXFeedFramework\/OrderSource\/agregateBid","doc:\/\/com.dxfeed.DXFeedFramework\/documentation\/DXFeedFramework\/OrderSource\/arca-2afur","doc:\/\/com.dxfeed.DXFeedFramework\/documentation\/DXFeedFramework\/OrderSource\/bzx-4dv0s","doc:\/\/com.dxfeed.DXFeedFramework\/documentation\/DXFeedFramework\/OrderSource\/cedx-psf9","doc:\/\/com.dxfeed.DXFeedFramework\/documentation\/DXFeedFramework\/OrderSource\/compsoiteAsk","doc:\/\/com.dxfeed.DXFeedFramework\/documentation\/DXFeedFramework\/OrderSource\/compsoiteBid","doc:\/\/com.dxfeed.DXFeedFramework\/documentation\/DXFeedFramework\/OrderSource\/defaultOrderSource","doc:\/\/com.dxfeed.DXFeedFramework\/documentation\/DXFeedFramework\/OrderSource\/dex-866to","doc:\/\/com.dxfeed.DXFeedFramework\/documentation\/DXFeedFramework\/OrderSource\/glbx-4gcnq","doc:\/\/com.dxfeed.DXFeedFramework\/documentation\/DXFeedFramework\/OrderSource\/iex","doc:\/\/com.dxfeed.DXFeedFramework\/documentation\/DXFeedFramework\/OrderSource\/memx-9dof4","doc:\/\/com.dxfeed.DXFeedFramework\/documentation\/DXFeedFramework\/OrderSource\/ntv-7392b","doc:\/\/com.dxfeed.DXFeedFramework\/documentation\/DXFeedFramework\/OrderSource\/pink","doc:\/\/com.dxfeed.DXFeedFramework\/documentation\/DXFeedFramework\/OrderSource\/regionalAsk","doc:\/\/com.dxfeed.DXFeedFramework\/documentation\/DXFeedFramework\/OrderSource\/regionalBid","doc:\/\/com.dxfeed.DXFeedFramework\/documentation\/DXFeedFramework\/OrderSource\/smfe-2a6vf","doc:\/\/com.dxfeed.DXFeedFramework\/documentation\/DXFeedFramework\/OrderSource\/xeur-81z2w"],"title":"Type Properties"},{"title":"Type Methods","identifiers":["doc:\/\/com.dxfeed.DXFeedFramework\/documentation\/DXFeedFramework\/OrderSource\/getEventTypeMask(_:)","doc:\/\/com.dxfeed.DXFeedFramework\/documentation\/DXFeedFramework\/OrderSource\/publishable(eventType:)","doc:\/\/com.dxfeed.DXFeedFramework\/documentation\/DXFeedFramework\/OrderSource\/valueOf(identifier:)","doc:\/\/com.dxfeed.DXFeedFramework\/documentation\/DXFeedFramework\/OrderSource\/valueOf(name:)"]}],"primaryContentSections":[{"kind":"declarations","declarations":[{"languages":["swift"],"platforms":["macOS"],"tokens":[{"kind":"keyword","text":"class"},{"text":" ","kind":"text"},{"kind":"identifier","text":"OrderSource"}]}]},{"kind":"content","content":[{"anchor":"overview","type":"heading","level":2,"text":"Overview"},{"type":"paragraph","inlineContent":[{"type":"text","text":"There are the following kinds of order sources:"}]},{"inlineContent":[{"text":"Synthetic sources ","type":"text"},{"identifier":"doc:\/\/com.dxfeed.DXFeedFramework\/documentation\/DXFeedFramework\/OrderSource\/compsoiteBid","type":"reference","isActive":true},{"type":"text","text":", "},{"type":"reference","identifier":"doc:\/\/com.dxfeed.DXFeedFramework\/documentation\/DXFeedFramework\/OrderSource\/compsoiteAsk","isActive":true},{"text":",","type":"text"},{"type":"text","text":" "},{"identifier":"doc:\/\/com.dxfeed.DXFeedFramework\/documentation\/DXFeedFramework\/OrderSource\/regionalBid","isActive":true,"type":"reference"},{"type":"text","text":", and "},{"type":"reference","identifier":"doc:\/\/com.dxfeed.DXFeedFramework\/documentation\/DXFeedFramework\/OrderSource\/regionalAsk","isActive":true},{"type":"text","text":" are provided for convenience of a consolidated"},{"type":"text","text":" "},{"text":"order book and are automatically generated based on the corresponding ","type":"text"},{"type":"reference","identifier":"doc:\/\/com.dxfeed.DXFeedFramework\/documentation\/DXFeedFramework\/Quote","isActive":true},{"type":"text","text":" events."},{"text":" ","type":"text"},{"type":"text","text":"Aggregate sources "},{"type":"reference","isActive":true,"identifier":"doc:\/\/com.dxfeed.DXFeedFramework\/documentation\/DXFeedFramework\/OrderSource\/agregateBid"},{"type":"text","text":" and "},{"identifier":"doc:\/\/com.dxfeed.DXFeedFramework\/documentation\/DXFeedFramework\/OrderSource\/agregateAsk","isActive":true,"type":"reference"},{"type":"text","text":" provide"},{"text":" ","type":"text"},{"text":"futures depth (aggregated by price level) and NASDAQ Level II (top of book for each market maker).","type":"text"},{"text":" ","type":"text"},{"text":"These source cannot be directly published to via dxFeed API.","type":"text"},{"text":" ","type":"text"},{"type":"reference","isActive":true,"identifier":"doc:\/\/com.dxfeed.DXFeedFramework\/documentation\/DXFeedFramework\/OrderSource\/isPublishable(eventType:)"},{"text":" sources ","type":"text"},{"isActive":true,"type":"reference","identifier":"doc:\/\/com.dxfeed.DXFeedFramework\/documentation\/DXFeedFramework\/OrderSource\/defaultOrderSource"},{"type":"text","text":", "},{"identifier":"doc:\/\/com.dxfeed.DXFeedFramework\/documentation\/DXFeedFramework\/OrderSource\/NTV-773uf","type":"reference","isActive":true},{"text":", and ","type":"text"},{"identifier":"doc:\/\/com.dxfeed.DXFeedFramework\/documentation\/DXFeedFramework\/OrderSource\/ISE","isActive":true,"type":"reference"},{"type":"text","text":" "},{"text":"support full range of dxFeed API features.","type":"text"}],"type":"paragraph"}]}],"hierarchy":{"paths":[["doc:\/\/com.dxfeed.DXFeedFramework\/documentation\/DXFeedFramework"]]},"metadata":{"navigatorTitle":[{"kind":"identifier","text":"OrderSource"}],"fragments":[{"text":"class","kind":"keyword"},{"kind":"text","text":" "},{"text":"OrderSource","kind":"identifier"}],"roleHeading":"Class","role":"symbol","modules":[{"name":"DXFeedFramework"}],"title":"OrderSource","externalID":"s:15DXFeedFramework11OrderSourceC","symbolKind":"class"},"variants":[{"paths":["\/documentation\/dxfeedframework\/ordersource"],"traits":[{"interfaceLanguage":"swift"}]}],"relationshipsSections":[{"type":"inheritsFrom","title":"Inherits From","identifiers":["doc:\/\/com.dxfeed.DXFeedFramework\/documentation\/DXFeedFramework\/IndexedEventSource"],"kind":"relationships"},{"identifiers":["doc:\/\/com.dxfeed.DXFeedFramework\/SQ"],"title":"Conforms To","type":"conformsTo","kind":"relationships"}],"schemaVersion":{"major":0,"minor":3,"patch":0},"identifier":{"interfaceLanguage":"swift","url":"doc:\/\/com.dxfeed.DXFeedFramework\/documentation\/DXFeedFramework\/OrderSource"},"sections":[],"references":{"doc://com.dxfeed.DXFeedFramework/SQ":{"type":"unresolvable","identifier":"doc:\/\/com.dxfeed.DXFeedFramework\/SQ","title":"Swift.Equatable"},"doc://com.dxfeed.DXFeedFramework/documentation/DXFeedFramework/AnalyticOrder/icebergExecutedSize":{"kind":"symbol","fragments":[{"kind":"keyword","text":"var"},{"text":" ","kind":"text"},{"kind":"identifier","text":"icebergExecutedSize"},{"kind":"text","text":": "},{"preciseIdentifier":"s:Sd","text":"Double","kind":"typeIdentifier"}],"abstract":[{"text":"Gets or sets iceberg executed size of this analytic order.","type":"text"}],"title":"icebergExecutedSize","identifier":"doc:\/\/com.dxfeed.DXFeedFramework\/documentation\/DXFeedFramework\/AnalyticOrder\/icebergExecutedSize","url":"\/documentation\/dxfeedframework\/analyticorder\/icebergexecutedsize","type":"topic","role":"symbol"},"doc://com.dxfeed.DXFeedFramework/documentation/DXFeedFramework/OrderSource/xeur-81z2w":{"fragments":[{"kind":"keyword","text":"static"},{"kind":"text","text":" "},{"text":"let","kind":"keyword"},{"kind":"text","text":" "},{"kind":"identifier","text":"xeur"},{"kind":"text","text":": "},{"kind":"typeIdentifier","text":"OrderSource","preciseIdentifier":"s:15DXFeedFramework11OrderSourceC"},{"text":"?","kind":"text"}],"type":"topic","identifier":"doc:\/\/com.dxfeed.DXFeedFramework\/documentation\/DXFeedFramework\/OrderSource\/xeur-81z2w","abstract":[{"type":"text","text":"Eurex Exchange. Record for price level book."}],"url":"\/documentation\/dxfeedframework\/ordersource\/xeur-81z2w","kind":"symbol","title":"xeur","role":"symbol"},"doc://com.dxfeed.DXFeedFramework/documentation/DXFeedFramework/OrderSource/regionalBid":{"title":"regionalBid","abstract":[{"type":"text","text":"Bid side of a regional "},{"type":"reference","isActive":true,"identifier":"doc:\/\/com.dxfeed.DXFeedFramework\/documentation\/DXFeedFramework\/Quote"},{"type":"text","text":"."},{"type":"text","text":" "},{"type":"text","text":"It is a synthetic source."},{"text":" ","type":"text"},{"text":"The subscription on regional ","type":"text"},{"type":"reference","identifier":"doc:\/\/com.dxfeed.DXFeedFramework\/documentation\/DXFeedFramework\/Quote","isActive":true},{"type":"text","text":" event is observed when this source is subscribed to."}],"url":"\/documentation\/dxfeedframework\/ordersource\/regionalbid","kind":"symbol","fragments":[{"text":"static","kind":"keyword"},{"text":" ","kind":"text"},{"kind":"keyword","text":"let"},{"kind":"text","text":" "},{"kind":"identifier","text":"regionalBid"},{"text":": ","kind":"text"},{"preciseIdentifier":"s:15DXFeedFramework11OrderSourceC","kind":"typeIdentifier","text":"OrderSource"},{"text":"?","kind":"text"}],"role":"symbol","type":"topic","identifier":"doc:\/\/com.dxfeed.DXFeedFramework\/documentation\/DXFeedFramework\/OrderSource\/regionalBid"},"doc://com.dxfeed.DXFeedFramework/documentation/DXFeedFramework/OrderSource/glbx-4gcnq":{"fragments":[{"text":"static","kind":"keyword"},{"text":" ","kind":"text"},{"kind":"keyword","text":"let"},{"text":" ","kind":"text"},{"kind":"identifier","text":"glbx"},{"text":": ","kind":"text"},{"text":"OrderSource","kind":"typeIdentifier","preciseIdentifier":"s:15DXFeedFramework11OrderSourceC"},{"kind":"text","text":"?"}],"role":"symbol","title":"glbx","type":"topic","kind":"symbol","url":"\/documentation\/dxfeedframework\/ordersource\/glbx-4gcnq","abstract":[{"text":"CME Globex. Record for price level book.","type":"text"}],"identifier":"doc:\/\/com.dxfeed.DXFeedFramework\/documentation\/DXFeedFramework\/OrderSource\/glbx-4gcnq"},"doc://com.dxfeed.DXFeedFramework/documentation/DXFeedFramework/OrderSource/ABE":{"abstract":[{"type":"text","text":"ABE (abe.io) exchange."}],"role":"symbol","type":"topic","fragments":[{"kind":"keyword","text":"static"},{"kind":"text","text":" "},{"kind":"keyword","text":"let"},{"text":" ","kind":"text"},{"text":"ABE","kind":"identifier"},{"kind":"text","text":": "},{"text":"OrderSource","preciseIdentifier":"s:15DXFeedFramework11OrderSourceC","kind":"typeIdentifier"},{"text":"?","kind":"text"}],"kind":"symbol","url":"\/documentation\/dxfeedframework\/ordersource\/abe","title":"ABE","identifier":"doc:\/\/com.dxfeed.DXFeedFramework\/documentation\/DXFeedFramework\/OrderSource\/ABE"},"doc://com.dxfeed.DXFeedFramework/documentation/DXFeedFramework/OrderSource/OCEA":{"role":"symbol","kind":"symbol","abstract":[{"type":"text","text":"Blue Ocean Technologies Alternative Trading System."}],"identifier":"doc:\/\/com.dxfeed.DXFeedFramework\/documentation\/DXFeedFramework\/OrderSource\/OCEA","fragments":[{"text":"static","kind":"keyword"},{"kind":"text","text":" "},{"kind":"keyword","text":"let"},{"kind":"text","text":" "},{"kind":"identifier","text":"OCEA"},{"text":": ","kind":"text"},{"kind":"typeIdentifier","text":"OrderSource","preciseIdentifier":"s:15DXFeedFramework11OrderSourceC"},{"kind":"text","text":"?"}],"url":"\/documentation\/dxfeedframework\/ordersource\/ocea","type":"topic","title":"OCEA"},"doc://com.dxfeed.DXFeedFramework/documentation/DXFeedFramework/OrderSource/BATE":{"role":"symbol","kind":"symbol","abstract":[{"text":"Bats Europe BXE Exchange.","type":"text"}],"identifier":"doc:\/\/com.dxfeed.DXFeedFramework\/documentation\/DXFeedFramework\/OrderSource\/BATE","fragments":[{"kind":"keyword","text":"static"},{"kind":"text","text":" "},{"text":"let","kind":"keyword"},{"kind":"text","text":" "},{"text":"BATE","kind":"identifier"},{"kind":"text","text":": "},{"kind":"typeIdentifier","text":"OrderSource","preciseIdentifier":"s:15DXFeedFramework11OrderSourceC"},{"text":"?","kind":"text"}],"type":"topic","url":"\/documentation\/dxfeedframework\/ordersource\/bate","title":"BATE"},"doc://com.dxfeed.DXFeedFramework/documentation/DXFeedFramework/OrderSource/IST":{"role":"symbol","fragments":[{"text":"static","kind":"keyword"},{"text":" ","kind":"text"},{"kind":"keyword","text":"let"},{"kind":"text","text":" "},{"kind":"identifier","text":"IST"},{"text":": ","kind":"text"},{"text":"OrderSource","kind":"typeIdentifier","preciseIdentifier":"s:15DXFeedFramework11OrderSourceC"},{"text":"?","kind":"text"}],"type":"topic","identifier":"doc:\/\/com.dxfeed.DXFeedFramework\/documentation\/DXFeedFramework\/OrderSource\/IST","kind":"symbol","abstract":[{"text":"Borsa Istanbul Exchange.","type":"text"}],"title":"IST","url":"\/documentation\/dxfeedframework\/ordersource\/ist"},"doc://com.dxfeed.DXFeedFramework/documentation/DXFeedFramework/OrderSource/iex":{"kind":"symbol","fragments":[{"text":"static","kind":"keyword"},{"text":" ","kind":"text"},{"text":"let","kind":"keyword"},{"text":" ","kind":"text"},{"kind":"identifier","text":"iex"},{"text":": ","kind":"text"},{"kind":"typeIdentifier","text":"OrderSource","preciseIdentifier":"s:15DXFeedFramework11OrderSourceC"},{"text":"?","kind":"text"}],"abstract":[{"text":"Investors exchange. Record for price level book.","type":"text"}],"title":"iex","identifier":"doc:\/\/com.dxfeed.DXFeedFramework\/documentation\/DXFeedFramework\/OrderSource\/iex","url":"\/documentation\/dxfeedframework\/ordersource\/iex","type":"topic","role":"symbol"},"doc://com.dxfeed.DXFeedFramework/documentation/DXFeedFramework/OrderSource/BZX-1fl38":{"role":"symbol","fragments":[{"text":"static","kind":"keyword"},{"kind":"text","text":" "},{"text":"let","kind":"keyword"},{"kind":"text","text":" "},{"text":"BZX","kind":"identifier"},{"kind":"text","text":": "},{"kind":"typeIdentifier","preciseIdentifier":"s:15DXFeedFramework11OrderSourceC","text":"OrderSource"},{"kind":"text","text":"?"}],"type":"topic","identifier":"doc:\/\/com.dxfeed.DXFeedFramework\/documentation\/DXFeedFramework\/OrderSource\/BZX-1fl38","kind":"symbol","abstract":[{"type":"text","text":"Bats BZX Exchange."}],"title":"BZX","url":"\/documentation\/dxfeedframework\/ordersource\/bzx-1fl38"},"doc://com.dxfeed.DXFeedFramework/documentation/DXFeedFramework/OrderSource/FAIR":{"kind":"symbol","identifier":"doc:\/\/com.dxfeed.DXFeedFramework\/documentation\/DXFeedFramework\/OrderSource\/FAIR","fragments":[{"text":"static","kind":"keyword"},{"text":" ","kind":"text"},{"text":"let","kind":"keyword"},{"kind":"text","text":" "},{"kind":"identifier","text":"FAIR"},{"kind":"text","text":": "},{"preciseIdentifier":"s:15DXFeedFramework11OrderSourceC","text":"OrderSource","kind":"typeIdentifier"},{"kind":"text","text":"?"}],"abstract":[{"type":"text","text":"FAIR (FairX) exchange."}],"url":"\/documentation\/dxfeedframework\/ordersource\/fair","type":"topic","role":"symbol","title":"FAIR"},"doc://com.dxfeed.DXFeedFramework/documentation/DXFeedFramework/OrderSource/cedx-psf9":{"role":"symbol","kind":"symbol","abstract":[{"type":"text","text":"Cboe European Derivatives. Record for price level book."}],"identifier":"doc:\/\/com.dxfeed.DXFeedFramework\/documentation\/DXFeedFramework\/OrderSource\/cedx-psf9","fragments":[{"kind":"keyword","text":"static"},{"text":" ","kind":"text"},{"kind":"keyword","text":"let"},{"text":" ","kind":"text"},{"text":"cedx","kind":"identifier"},{"kind":"text","text":": "},{"kind":"typeIdentifier","text":"OrderSource","preciseIdentifier":"s:15DXFeedFramework11OrderSourceC"},{"text":"?","kind":"text"}],"type":"topic","url":"\/documentation\/dxfeedframework\/ordersource\/cedx-psf9","title":"cedx"},"doc://com.dxfeed.DXFeedFramework/documentation/DXFeedFramework/OrderSource/defaultOrderSource":{"title":"defaultOrderSource","abstract":[{"type":"text","text":"The default source with zero identifier for all events that do not support multiple sources."}],"url":"\/documentation\/dxfeedframework\/ordersource\/defaultordersource","role":"symbol","type":"topic","kind":"symbol","identifier":"doc:\/\/com.dxfeed.DXFeedFramework\/documentation\/DXFeedFramework\/OrderSource\/defaultOrderSource","fragments":[{"text":"static","kind":"keyword"},{"kind":"text","text":" "},{"text":"let","kind":"keyword"},{"kind":"text","text":" "},{"text":"defaultOrderSource","kind":"identifier"},{"text":": ","kind":"text"},{"preciseIdentifier":"s:15DXFeedFramework11OrderSourceC","kind":"typeIdentifier","text":"OrderSource"},{"kind":"text","text":"?"}]},"doc://com.dxfeed.DXFeedFramework/documentation/DXFeedFramework/Quote":{"kind":"symbol","fragments":[{"text":"class","kind":"keyword"},{"text":" ","kind":"text"},{"kind":"identifier","text":"Quote"}],"url":"\/documentation\/dxfeedframework\/quote","type":"topic","identifier":"doc:\/\/com.dxfeed.DXFeedFramework\/documentation\/DXFeedFramework\/Quote","role":"symbol","title":"Quote","navigatorTitle":[{"kind":"identifier","text":"Quote"}],"abstract":[{"type":"text","text":"Quote event is a snapshot of the best bid and ask prices, and other fields that change with each quote."}]},"doc://com.dxfeed.DXFeedFramework/documentation/DXFeedFramework/OrderSource/ARCA-2h2y5":{"fragments":[{"kind":"keyword","text":"static"},{"kind":"text","text":" "},{"kind":"keyword","text":"let"},{"kind":"text","text":" "},{"text":"ARCA","kind":"identifier"},{"text":": ","kind":"text"},{"preciseIdentifier":"s:15DXFeedFramework11OrderSourceC","kind":"typeIdentifier","text":"OrderSource"},{"kind":"text","text":"?"}],"type":"topic","identifier":"doc:\/\/com.dxfeed.DXFeedFramework\/documentation\/DXFeedFramework\/OrderSource\/ARCA-2h2y5","abstract":[{"type":"text","text":"NYSE Arca traded securities."}],"kind":"symbol","url":"\/documentation\/dxfeedframework\/ordersource\/arca-2h2y5","title":"ARCA","role":"symbol"},"doc://com.dxfeed.DXFeedFramework/documentation/DXFeedFramework/OrderSource/GLBX-8ulae":{"title":"GLBX","identifier":"doc:\/\/com.dxfeed.DXFeedFramework\/documentation\/DXFeedFramework\/OrderSource\/GLBX-8ulae","role":"symbol","type":"topic","abstract":[{"text":"CME Globex.","type":"text"}],"kind":"symbol","fragments":[{"text":"static","kind":"keyword"},{"text":" ","kind":"text"},{"text":"let","kind":"keyword"},{"text":" ","kind":"text"},{"text":"GLBX","kind":"identifier"},{"kind":"text","text":": "},{"text":"OrderSource","kind":"typeIdentifier","preciseIdentifier":"s:15DXFeedFramework11OrderSourceC"},{"kind":"text","text":"?"}],"url":"\/documentation\/dxfeedframework\/ordersource\/glbx-8ulae"},"doc://com.dxfeed.DXFeedFramework/documentation/DXFeedFramework":{"title":"DXFeedFramework","url":"\/documentation\/dxfeedframework","identifier":"doc:\/\/com.dxfeed.DXFeedFramework\/documentation\/DXFeedFramework","abstract":[],"kind":"symbol","type":"topic","role":"collection"},"doc://com.dxfeed.DXFeedFramework/documentation/DXFeedFramework/OrderSource/ESPD":{"role":"symbol","fragments":[{"text":"static","kind":"keyword"},{"kind":"text","text":" "},{"kind":"keyword","text":"let"},{"kind":"text","text":" "},{"kind":"identifier","text":"ESPD"},{"text":": ","kind":"text"},{"kind":"typeIdentifier","preciseIdentifier":"s:15DXFeedFramework11OrderSourceC","text":"OrderSource"},{"kind":"text","text":"?"}],"type":"topic","identifier":"doc:\/\/com.dxfeed.DXFeedFramework\/documentation\/DXFeedFramework\/OrderSource\/ESPD","kind":"symbol","abstract":[{"text":"NASDAQ eSpeed.","type":"text"}],"url":"\/documentation\/dxfeedframework\/ordersource\/espd","title":"ESPD"},"doc://com.dxfeed.DXFeedFramework/documentation/DXFeedFramework/OrderSource/getEventTypeMask(_:)":{"url":"\/documentation\/dxfeedframework\/ordersource\/geteventtypemask(_:)","fragments":[{"text":"static","kind":"keyword"},{"kind":"text","text":" "},{"text":"func","kind":"keyword"},{"text":" ","kind":"text"},{"kind":"identifier","text":"getEventTypeMask"},{"kind":"text","text":"("},{"kind":"typeIdentifier","preciseIdentifier":"s:s8AnyClassa","text":"AnyClass"},{"text":") ","kind":"text"},{"kind":"keyword","text":"throws"},{"kind":"text","text":" -> "},{"preciseIdentifier":"s:Si","kind":"typeIdentifier","text":"Int"}],"title":"getEventTypeMask(_:)","identifier":"doc:\/\/com.dxfeed.DXFeedFramework\/documentation\/DXFeedFramework\/OrderSource\/getEventTypeMask(_:)","kind":"symbol","type":"topic","abstract":[{"type":"text","text":"Gets type mask by specified event type."}],"role":"symbol"},"doc://com.dxfeed.DXFeedFramework/documentation/DXFeedFramework/SpreadOrder":{"type":"topic","identifier":"doc:\/\/com.dxfeed.DXFeedFramework\/documentation\/DXFeedFramework\/SpreadOrder","fragments":[{"kind":"keyword","text":"class"},{"kind":"text","text":" "},{"kind":"identifier","text":"SpreadOrder"}],"title":"SpreadOrder","abstract":[{"text":"Spread order event is a snapshot for a full available market depth for all spreads","type":"text"},{"text":" ","type":"text"},{"text":"on a given underlying symbol.","type":"text"}],"url":"\/documentation\/dxfeedframework\/spreadorder","kind":"symbol","navigatorTitle":[{"kind":"identifier","text":"SpreadOrder"}],"role":"symbol"},"doc://com.dxfeed.DXFeedFramework/documentation/DXFeedFramework/OrderSource/C2OX":{"type":"topic","kind":"symbol","title":"C2OX","url":"\/documentation\/dxfeedframework\/ordersource\/c2ox","role":"symbol","fragments":[{"kind":"keyword","text":"static"},{"text":" ","kind":"text"},{"text":"let","kind":"keyword"},{"kind":"text","text":" "},{"text":"C2OX","kind":"identifier"},{"text":": ","kind":"text"},{"text":"OrderSource","kind":"typeIdentifier","preciseIdentifier":"s:15DXFeedFramework11OrderSourceC"},{"kind":"text","text":"?"}],"abstract":[{"type":"text","text":"CBOE Options C2 Exchange."}],"identifier":"doc:\/\/com.dxfeed.DXFeedFramework\/documentation\/DXFeedFramework\/OrderSource\/C2OX"},"doc://com.dxfeed.DXFeedFramework/documentation/DXFeedFramework/OrderSource/BI20":{"title":"BI20","identifier":"doc:\/\/com.dxfeed.DXFeedFramework\/documentation\/DXFeedFramework\/OrderSource\/BI20","role":"symbol","type":"topic","abstract":[{"type":"text","text":"Borsa Istanbul Exchange. Record for particular top 20 order book."}],"kind":"symbol","fragments":[{"text":"static","kind":"keyword"},{"kind":"text","text":" "},{"kind":"keyword","text":"let"},{"text":" ","kind":"text"},{"kind":"identifier","text":"BI20"},{"text":": ","kind":"text"},{"kind":"typeIdentifier","text":"OrderSource","preciseIdentifier":"s:15DXFeedFramework11OrderSourceC"},{"text":"?","kind":"text"}],"url":"\/documentation\/dxfeedframework\/ordersource\/bi20"},"doc://com.dxfeed.DXFeedFramework/documentation/DXFeedFramework/OrderSource/CHIX":{"role":"symbol","fragments":[{"kind":"keyword","text":"static"},{"kind":"text","text":" "},{"kind":"keyword","text":"let"},{"text":" ","kind":"text"},{"text":"CHIX","kind":"identifier"},{"kind":"text","text":": "},{"kind":"typeIdentifier","text":"OrderSource","preciseIdentifier":"s:15DXFeedFramework11OrderSourceC"},{"text":"?","kind":"text"}],"type":"topic","identifier":"doc:\/\/com.dxfeed.DXFeedFramework\/documentation\/DXFeedFramework\/OrderSource\/CHIX","kind":"symbol","abstract":[{"type":"text","text":"Bats Europe CXE Exchange."}],"title":"CHIX","url":"\/documentation\/dxfeedframework\/ordersource\/chix"},"doc://com.dxfeed.DXFeedFramework/documentation/DXFeedFramework/OrderSource/agregateBid":{"role":"symbol","fragments":[{"kind":"keyword","text":"static"},{"text":" ","kind":"text"},{"text":"let","kind":"keyword"},{"kind":"text","text":" "},{"kind":"identifier","text":"agregateBid"},{"kind":"text","text":": "},{"text":"OrderSource","preciseIdentifier":"s:15DXFeedFramework11OrderSourceC","kind":"typeIdentifier"},{"text":"?","kind":"text"}],"type":"topic","identifier":"doc:\/\/com.dxfeed.DXFeedFramework\/documentation\/DXFeedFramework\/OrderSource\/agregateBid","kind":"symbol","abstract":[{"type":"text","text":"Bid side of an aggregate order book (futures depth and NASDAQ Level II)."},{"text":" ","type":"text"},{"type":"text","text":"This source cannot be directly published via dxFeed API, but otherwise it is fully operational."}],"url":"\/documentation\/dxfeedframework\/ordersource\/agregatebid","title":"agregateBid"},"doc://com.dxfeed.DXFeedFramework/documentation/DXFeedFramework/OrderSource/XEUR-fa6f":{"role":"symbol","kind":"symbol","abstract":[{"type":"text","text":"Eurex Exchange."}],"identifier":"doc:\/\/com.dxfeed.DXFeedFramework\/documentation\/DXFeedFramework\/OrderSource\/XEUR-fa6f","fragments":[{"text":"static","kind":"keyword"},{"kind":"text","text":" "},{"kind":"keyword","text":"let"},{"text":" ","kind":"text"},{"text":"XEUR","kind":"identifier"},{"text":": ","kind":"text"},{"preciseIdentifier":"s:15DXFeedFramework11OrderSourceC","kind":"typeIdentifier","text":"OrderSource"},{"text":"?","kind":"text"}],"url":"\/documentation\/dxfeedframework\/ordersource\/xeur-fa6f","type":"topic","title":"XEUR"},"doc://com.dxfeed.DXFeedFramework/documentation/DXFeedFramework/OrderSource/SMFE-2xqm":{"title":"SMFE","abstract":[{"type":"text","text":"Small Exchange."}],"url":"\/documentation\/dxfeedframework\/ordersource\/smfe-2xqm","role":"symbol","type":"topic","kind":"symbol","identifier":"doc:\/\/com.dxfeed.DXFeedFramework\/documentation\/DXFeedFramework\/OrderSource\/SMFE-2xqm","fragments":[{"text":"static","kind":"keyword"},{"kind":"text","text":" "},{"kind":"keyword","text":"let"},{"text":" ","kind":"text"},{"text":"SMFE","kind":"identifier"},{"text":": ","kind":"text"},{"text":"OrderSource","preciseIdentifier":"s:15DXFeedFramework11OrderSourceC","kind":"typeIdentifier"},{"kind":"text","text":"?"}]},"doc://com.dxfeed.DXFeedFramework/documentation/DXFeedFramework/OrderSource/MEMX-8i7t3":{"role":"symbol","fragments":[{"text":"static","kind":"keyword"},{"kind":"text","text":" "},{"text":"let","kind":"keyword"},{"kind":"text","text":" "},{"text":"MEMX","kind":"identifier"},{"text":": ","kind":"text"},{"text":"OrderSource","kind":"typeIdentifier","preciseIdentifier":"s:15DXFeedFramework11OrderSourceC"},{"text":"?","kind":"text"}],"type":"topic","identifier":"doc:\/\/com.dxfeed.DXFeedFramework\/documentation\/DXFeedFramework\/OrderSource\/MEMX-8i7t3","kind":"symbol","abstract":[{"text":"Members Exchange.","type":"text"}],"url":"\/documentation\/dxfeedframework\/ordersource\/memx-8i7t3","title":"MEMX"},"doc://com.dxfeed.DXFeedFramework/documentation/DXFeedFramework/OrderSource":{"kind":"symbol","identifier":"doc:\/\/com.dxfeed.DXFeedFramework\/documentation\/DXFeedFramework\/OrderSource","fragments":[{"text":"class","kind":"keyword"},{"text":" ","kind":"text"},{"kind":"identifier","text":"OrderSource"}],"type":"topic","url":"\/documentation\/dxfeedframework\/ordersource","abstract":[{"text":"Identifies source of ","type":"text"},{"type":"reference","identifier":"doc:\/\/com.dxfeed.DXFeedFramework\/documentation\/DXFeedFramework\/Order","isActive":true},{"type":"text","text":", "},{"identifier":"doc:\/\/com.dxfeed.DXFeedFramework\/documentation\/DXFeedFramework\/AnalyticOrder","type":"reference","isActive":true},{"text":", OtcMarketsOrder and ","type":"text"},{"isActive":true,"type":"reference","identifier":"doc:\/\/com.dxfeed.DXFeedFramework\/documentation\/DXFeedFramework\/SpreadOrder"},{"text":" events.","type":"text"}],"role":"symbol","title":"OrderSource","navigatorTitle":[{"kind":"identifier","text":"OrderSource"}]},"doc://com.dxfeed.DXFeedFramework/documentation/DXFeedFramework/OrderSource/memx-9dof4":{"role":"symbol","fragments":[{"text":"static","kind":"keyword"},{"kind":"text","text":" "},{"text":"let","kind":"keyword"},{"kind":"text","text":" "},{"kind":"identifier","text":"memx"},{"kind":"text","text":": "},{"kind":"typeIdentifier","preciseIdentifier":"s:15DXFeedFramework11OrderSourceC","text":"OrderSource"},{"text":"?","kind":"text"}],"type":"topic","identifier":"doc:\/\/com.dxfeed.DXFeedFramework\/documentation\/DXFeedFramework\/OrderSource\/memx-9dof4","kind":"symbol","abstract":[{"type":"text","text":"Members Exchange. Record for price level book."}],"url":"\/documentation\/dxfeedframework\/ordersource\/memx-9dof4","title":"memx"},"doc://com.dxfeed.DXFeedFramework/documentation/DXFeedFramework/OrderSource/isPublishable(eventType:)":{"role":"symbol","url":"\/documentation\/dxfeedframework\/ordersource\/ispublishable(eventtype:)","identifier":"doc:\/\/com.dxfeed.DXFeedFramework\/documentation\/DXFeedFramework\/OrderSource\/isPublishable(eventType:)","kind":"symbol","abstract":[{"type":"text","text":"Gets a value indicating whether the given event type can be directly published with this source."}],"fragments":[{"text":"func","kind":"keyword"},{"kind":"text","text":" "},{"kind":"identifier","text":"isPublishable"},{"kind":"text","text":"("},{"kind":"externalParam","text":"eventType"},{"kind":"text","text":": "},{"kind":"typeIdentifier","preciseIdentifier":"s:s8AnyClassa","text":"AnyClass"},{"text":".Type) ","kind":"text"},{"text":"throws","kind":"keyword"},{"text":" -> ","kind":"text"},{"kind":"typeIdentifier","text":"Bool","preciseIdentifier":"s:Sb"}],"type":"topic","title":"isPublishable(eventType:)"},"doc://com.dxfeed.DXFeedFramework/documentation/DXFeedFramework/OrderSource/CEDX-8i4o9":{"role":"symbol","fragments":[{"kind":"keyword","text":"static"},{"text":" ","kind":"text"},{"text":"let","kind":"keyword"},{"text":" ","kind":"text"},{"kind":"identifier","text":"CEDX"},{"kind":"text","text":": "},{"kind":"typeIdentifier","preciseIdentifier":"s:15DXFeedFramework11OrderSourceC","text":"OrderSource"},{"text":"?","kind":"text"}],"type":"topic","identifier":"doc:\/\/com.dxfeed.DXFeedFramework\/documentation\/DXFeedFramework\/OrderSource\/CEDX-8i4o9","kind":"symbol","abstract":[{"type":"text","text":"Cboe European Derivatives."}],"url":"\/documentation\/dxfeedframework\/ordersource\/cedx-8i4o9","title":"CEDX"},"doc://com.dxfeed.DXFeedFramework/documentation/DXFeedFramework/OrderSource/ERIS":{"type":"topic","kind":"symbol","title":"ERIS","url":"\/documentation\/dxfeedframework\/ordersource\/eris","role":"symbol","fragments":[{"text":"static","kind":"keyword"},{"text":" ","kind":"text"},{"text":"let","kind":"keyword"},{"text":" ","kind":"text"},{"kind":"identifier","text":"ERIS"},{"text":": ","kind":"text"},{"text":"OrderSource","kind":"typeIdentifier","preciseIdentifier":"s:15DXFeedFramework11OrderSourceC"},{"text":"?","kind":"text"}],"abstract":[{"type":"text","text":"Eris Exchange group of companies."}],"identifier":"doc:\/\/com.dxfeed.DXFeedFramework\/documentation\/DXFeedFramework\/OrderSource\/ERIS"},"doc://com.dxfeed.DXFeedFramework/documentation/DXFeedFramework/OrderSource/NTV-773uf":{"role":"symbol","fragments":[{"text":"static","kind":"keyword"},{"text":" ","kind":"text"},{"text":"let","kind":"keyword"},{"kind":"text","text":" "},{"text":"NTV","kind":"identifier"},{"kind":"text","text":": "},{"kind":"typeIdentifier","text":"OrderSource","preciseIdentifier":"s:15DXFeedFramework11OrderSourceC"},{"kind":"text","text":"?"}],"type":"topic","identifier":"doc:\/\/com.dxfeed.DXFeedFramework\/documentation\/DXFeedFramework\/OrderSource\/NTV-773uf","kind":"symbol","abstract":[{"type":"text","text":"NASDAQ Total View."}],"title":"NTV","url":"\/documentation\/dxfeedframework\/ordersource\/ntv-773uf"},"doc://com.dxfeed.DXFeedFramework/documentation/DXFeedFramework/OrderSource/regionalAsk":{"kind":"symbol","fragments":[{"text":"static","kind":"keyword"},{"text":" ","kind":"text"},{"kind":"keyword","text":"let"},{"text":" ","kind":"text"},{"text":"regionalAsk","kind":"identifier"},{"text":": ","kind":"text"},{"preciseIdentifier":"s:15DXFeedFramework11OrderSourceC","kind":"typeIdentifier","text":"OrderSource"},{"text":"?","kind":"text"}],"abstract":[{"type":"text","text":"Ask side of a regional "},{"type":"reference","identifier":"doc:\/\/com.dxfeed.DXFeedFramework\/documentation\/DXFeedFramework\/Quote","isActive":true},{"type":"text","text":"."},{"type":"text","text":" "},{"text":"It is a synthetic source.","type":"text"},{"type":"text","text":" "},{"text":"The subscription on regional ","type":"text"},{"type":"reference","identifier":"doc:\/\/com.dxfeed.DXFeedFramework\/documentation\/DXFeedFramework\/Quote","isActive":true},{"type":"text","text":" event is observed when this source is subscribed to."}],"title":"regionalAsk","identifier":"doc:\/\/com.dxfeed.DXFeedFramework\/documentation\/DXFeedFramework\/OrderSource\/regionalAsk","url":"\/documentation\/dxfeedframework\/ordersource\/regionalask","type":"topic","role":"symbol"},"doc://com.dxfeed.DXFeedFramework/documentation/DXFeedFramework/OrderSource/bzx-4dv0s":{"title":"bzx","type":"topic","fragments":[{"kind":"keyword","text":"static"},{"kind":"text","text":" "},{"kind":"keyword","text":"let"},{"kind":"text","text":" "},{"kind":"identifier","text":"bzx"},{"text":": ","kind":"text"},{"preciseIdentifier":"s:15DXFeedFramework11OrderSourceC","text":"OrderSource","kind":"typeIdentifier"},{"kind":"text","text":"?"}],"identifier":"doc:\/\/com.dxfeed.DXFeedFramework\/documentation\/DXFeedFramework\/OrderSource\/bzx-4dv0s","abstract":[{"text":"Bats BZX Exchange. Record for price level book.","type":"text"}],"kind":"symbol","role":"symbol","url":"\/documentation\/dxfeedframework\/ordersource\/bzx-4dv0s"},"doc://com.dxfeed.DXFeedFramework/documentation/DXFeedFramework/OrderSource/agregateAsk":{"abstract":[{"text":"Ask side of an aggregate order book (futures depth and NASDAQ Level II).","type":"text"},{"type":"text","text":" "},{"type":"text","text":"This source cannot be directly published via dxFeed API, but otherwise it is fully operational."}],"title":"agregateAsk","url":"\/documentation\/dxfeedframework\/ordersource\/agregateask","role":"symbol","type":"topic","identifier":"doc:\/\/com.dxfeed.DXFeedFramework\/documentation\/DXFeedFramework\/OrderSource\/agregateAsk","kind":"symbol","fragments":[{"text":"static","kind":"keyword"},{"text":" ","kind":"text"},{"text":"let","kind":"keyword"},{"kind":"text","text":" "},{"kind":"identifier","text":"agregateAsk"},{"text":": ","kind":"text"},{"text":"OrderSource","preciseIdentifier":"s:15DXFeedFramework11OrderSourceC","kind":"typeIdentifier"},{"kind":"text","text":"?"}]},"doc://com.dxfeed.DXFeedFramework/documentation/DXFeedFramework/Order":{"kind":"symbol","fragments":[{"text":"class","kind":"keyword"},{"text":" ","kind":"text"},{"kind":"identifier","text":"Order"}],"navigatorTitle":[{"kind":"identifier","text":"Order"}],"abstract":[{"text":"Order event is a snapshot for a full available market depth for a symbol.","type":"text"}],"title":"Order","identifier":"doc:\/\/com.dxfeed.DXFeedFramework\/documentation\/DXFeedFramework\/Order","url":"\/documentation\/dxfeedframework\/order","type":"topic","role":"symbol"},"doc://com.dxfeed.DXFeedFramework/documentation/DXFeedFramework/OrderSource/compsoiteAsk":{"role":"symbol","kind":"symbol","abstract":[{"text":"Ask side of a composite ","type":"text"},{"isActive":true,"type":"reference","identifier":"doc:\/\/com.dxfeed.DXFeedFramework\/documentation\/DXFeedFramework\/Quote"},{"type":"text","text":"."},{"text":" ","type":"text"},{"type":"text","text":"It is a synthetic source."},{"type":"text","text":" "},{"type":"text","text":"The subscription on composite "},{"type":"reference","identifier":"doc:\/\/com.dxfeed.DXFeedFramework\/documentation\/DXFeedFramework\/Quote","isActive":true},{"type":"text","text":" event is observed when this source is subscribed to."}],"identifier":"doc:\/\/com.dxfeed.DXFeedFramework\/documentation\/DXFeedFramework\/OrderSource\/compsoiteAsk","fragments":[{"kind":"keyword","text":"static"},{"text":" ","kind":"text"},{"kind":"keyword","text":"let"},{"kind":"text","text":" "},{"kind":"identifier","text":"compsoiteAsk"},{"text":": ","kind":"text"},{"text":"OrderSource","kind":"typeIdentifier","preciseIdentifier":"s:15DXFeedFramework11OrderSourceC"},{"text":"?","kind":"text"}],"url":"\/documentation\/dxfeedframework\/ordersource\/compsoiteask","type":"topic","title":"compsoiteAsk"},"doc://com.dxfeed.DXFeedFramework/documentation/DXFeedFramework/AnalyticOrder/icebergHiddenSize":{"kind":"symbol","fragments":[{"text":"var","kind":"keyword"},{"kind":"text","text":" "},{"kind":"identifier","text":"icebergHiddenSize"},{"text":": ","kind":"text"},{"kind":"typeIdentifier","preciseIdentifier":"s:Sd","text":"Double"}],"abstract":[{"type":"text","text":"Gets or sets iceberg hidden size of this analytic order."}],"title":"icebergHiddenSize","identifier":"doc:\/\/com.dxfeed.DXFeedFramework\/documentation\/DXFeedFramework\/AnalyticOrder\/icebergHiddenSize","url":"\/documentation\/dxfeedframework\/analyticorder\/iceberghiddensize","type":"topic","role":"symbol"},"doc://com.dxfeed.DXFeedFramework/documentation/DXFeedFramework/IIndexedEvent":{"type":"topic","identifier":"doc:\/\/com.dxfeed.DXFeedFramework\/documentation\/DXFeedFramework\/IIndexedEvent","fragments":[{"text":"protocol","kind":"keyword"},{"kind":"text","text":" "},{"kind":"identifier","text":"IIndexedEvent"}],"title":"IIndexedEvent","abstract":[{"text":"Represents an indexed collection of up-to-date information about some","type":"text"},{"text":" ","type":"text"},{"type":"text","text":"condition or state of an external entity that updates in real-time."}],"url":"\/documentation\/dxfeedframework\/iindexedevent","kind":"symbol","navigatorTitle":[{"kind":"identifier","text":"IIndexedEvent"}],"role":"symbol"},"doc://com.dxfeed.DXFeedFramework/documentation/DXFeedFramework/AnalyticOrder/icebergPeakSize":{"kind":"symbol","fragments":[{"text":"var","kind":"keyword"},{"kind":"text","text":" "},{"kind":"identifier","text":"icebergPeakSize"},{"text":": ","kind":"text"},{"kind":"typeIdentifier","preciseIdentifier":"s:Sd","text":"Double"}],"abstract":[{"text":"Gets or sets iceberg peak size of this analytic order.","type":"text"}],"title":"icebergPeakSize","identifier":"doc:\/\/com.dxfeed.DXFeedFramework\/documentation\/DXFeedFramework\/AnalyticOrder\/icebergPeakSize","url":"\/documentation\/dxfeedframework\/analyticorder\/icebergpeaksize","type":"topic","role":"symbol"},"doc://com.dxfeed.DXFeedFramework/documentation/DXFeedFramework/OrderSource/pink":{"kind":"symbol","type":"topic","fragments":[{"text":"static","kind":"keyword"},{"text":" ","kind":"text"},{"text":"let","kind":"keyword"},{"text":" ","kind":"text"},{"text":"pink","kind":"identifier"},{"text":": ","kind":"text"},{"text":"OrderSource","kind":"typeIdentifier","preciseIdentifier":"s:15DXFeedFramework11OrderSourceC"},{"kind":"text","text":"?"}],"identifier":"doc:\/\/com.dxfeed.DXFeedFramework\/documentation\/DXFeedFramework\/OrderSource\/pink","abstract":[{"text":"Pink Sheets. Record for price level book.","type":"text"},{"text":" ","type":"text"},{"text":"Pink sheets are listings for stocks that trade over-the-counter (OTC).","type":"text"}],"url":"\/documentation\/dxfeedframework\/ordersource\/pink","title":"pink","role":"symbol"},"doc://com.dxfeed.DXFeedFramework/documentation/DXFeedFramework/OrderSource/ntv-7392b":{"kind":"symbol","identifier":"doc:\/\/com.dxfeed.DXFeedFramework\/documentation\/DXFeedFramework\/OrderSource\/ntv-7392b","fragments":[{"text":"static","kind":"keyword"},{"text":" ","kind":"text"},{"text":"let","kind":"keyword"},{"kind":"text","text":" "},{"kind":"identifier","text":"ntv"},{"text":": ","kind":"text"},{"text":"OrderSource","kind":"typeIdentifier","preciseIdentifier":"s:15DXFeedFramework11OrderSourceC"},{"kind":"text","text":"?"}],"type":"topic","url":"\/documentation\/dxfeedframework\/ordersource\/ntv-7392b","abstract":[{"text":"NASDAQ Total View. Record for price level book.","type":"text"}],"role":"symbol","title":"ntv"},"doc://com.dxfeed.DXFeedFramework/documentation/DXFeedFramework/OrderSource/valueOf(identifier:)":{"role":"symbol","fragments":[{"kind":"keyword","text":"static"},{"text":" ","kind":"text"},{"text":"func","kind":"keyword"},{"kind":"text","text":" "},{"text":"valueOf","kind":"identifier"},{"text":"(","kind":"text"},{"text":"identifier","kind":"externalParam"},{"kind":"text","text":": "},{"preciseIdentifier":"s:Si","kind":"typeIdentifier","text":"Int"},{"text":") ","kind":"text"},{"text":"throws","kind":"keyword"},{"text":" -> ","kind":"text"},{"kind":"typeIdentifier","text":"OrderSource","preciseIdentifier":"s:15DXFeedFramework11OrderSourceC"}],"url":"\/documentation\/dxfeedframework\/ordersource\/valueof(identifier:)","identifier":"doc:\/\/com.dxfeed.DXFeedFramework\/documentation\/DXFeedFramework\/OrderSource\/valueOf(identifier:)","title":"valueOf(identifier:)","abstract":[{"text":"Returns order source for the specified source identifier.","type":"text"}],"type":"topic","kind":"symbol"},"doc://com.dxfeed.DXFeedFramework/documentation/DXFeedFramework/OrderSource/CFE":{"role":"symbol","fragments":[{"text":"static","kind":"keyword"},{"text":" ","kind":"text"},{"text":"let","kind":"keyword"},{"kind":"text","text":" "},{"kind":"identifier","text":"CFE"},{"kind":"text","text":": "},{"text":"OrderSource","preciseIdentifier":"s:15DXFeedFramework11OrderSourceC","kind":"typeIdentifier"},{"text":"?","kind":"text"}],"type":"topic","identifier":"doc:\/\/com.dxfeed.DXFeedFramework\/documentation\/DXFeedFramework\/OrderSource\/CFE","kind":"symbol","abstract":[{"type":"text","text":"CBOE Futures Exchange."}],"url":"\/documentation\/dxfeedframework\/ordersource\/cfe","title":"CFE"},"doc://com.dxfeed.DXFeedFramework/documentation/DXFeedFramework/OrderSource/CEUX":{"role":"symbol","fragments":[{"kind":"keyword","text":"static"},{"kind":"text","text":" "},{"text":"let","kind":"keyword"},{"text":" ","kind":"text"},{"text":"CEUX","kind":"identifier"},{"text":": ","kind":"text"},{"text":"OrderSource","kind":"typeIdentifier","preciseIdentifier":"s:15DXFeedFramework11OrderSourceC"},{"kind":"text","text":"?"}],"type":"topic","identifier":"doc:\/\/com.dxfeed.DXFeedFramework\/documentation\/DXFeedFramework\/OrderSource\/CEUX","kind":"symbol","abstract":[{"type":"text","text":"Bats Europe DXE Exchange."}],"url":"\/documentation\/dxfeedframework\/ordersource\/ceux","title":"CEUX"},"doc://com.dxfeed.DXFeedFramework/documentation/DXFeedFramework/IndexedEventSource":{"kind":"symbol","fragments":[{"text":"class","kind":"keyword"},{"text":" ","kind":"text"},{"text":"IndexedEventSource","kind":"identifier"}],"url":"\/documentation\/dxfeedframework\/indexedeventsource","type":"topic","identifier":"doc:\/\/com.dxfeed.DXFeedFramework\/documentation\/DXFeedFramework\/IndexedEventSource","role":"symbol","title":"IndexedEventSource","navigatorTitle":[{"text":"IndexedEventSource","kind":"identifier"}],"abstract":[{"type":"text","text":"Source identifier for "},{"isActive":true,"type":"reference","identifier":"doc:\/\/com.dxfeed.DXFeedFramework\/documentation\/DXFeedFramework\/IIndexedEvent"},{"type":"text","text":"."}]},"doc://com.dxfeed.DXFeedFramework/documentation/DXFeedFramework/OrderSource/NFX":{"role":"symbol","kind":"symbol","abstract":[{"type":"text","text":"NASDAQ Futures Exchange."}],"identifier":"doc:\/\/com.dxfeed.DXFeedFramework\/documentation\/DXFeedFramework\/OrderSource\/NFX","fragments":[{"kind":"keyword","text":"static"},{"kind":"text","text":" "},{"kind":"keyword","text":"let"},{"text":" ","kind":"text"},{"text":"NFX","kind":"identifier"},{"text":": ","kind":"text"},{"kind":"typeIdentifier","text":"OrderSource","preciseIdentifier":"s:15DXFeedFramework11OrderSourceC"},{"text":"?","kind":"text"}],"type":"topic","url":"\/documentation\/dxfeedframework\/ordersource\/nfx","title":"NFX"},"doc://com.dxfeed.DXFeedFramework/documentation/DXFeedFramework/OrderSource/arca-2afur":{"kind":"symbol","type":"topic","fragments":[{"text":"static","kind":"keyword"},{"text":" ","kind":"text"},{"text":"let","kind":"keyword"},{"kind":"text","text":" "},{"kind":"identifier","text":"arca"},{"kind":"text","text":": "},{"preciseIdentifier":"s:15DXFeedFramework11OrderSourceC","text":"OrderSource","kind":"typeIdentifier"},{"kind":"text","text":"?"}],"identifier":"doc:\/\/com.dxfeed.DXFeedFramework\/documentation\/DXFeedFramework\/OrderSource\/arca-2afur","url":"\/documentation\/dxfeedframework\/ordersource\/arca-2afur","abstract":[{"text":"NYSE Arca traded securities.. Record for price level book.","type":"text"}],"title":"arca","role":"symbol"},"doc://com.dxfeed.DXFeedFramework/documentation/DXFeedFramework/OrderSource/compsoiteBid":{"kind":"symbol","identifier":"doc:\/\/com.dxfeed.DXFeedFramework\/documentation\/DXFeedFramework\/OrderSource\/compsoiteBid","fragments":[{"kind":"keyword","text":"static"},{"text":" ","kind":"text"},{"text":"let","kind":"keyword"},{"text":" ","kind":"text"},{"kind":"identifier","text":"compsoiteBid"},{"kind":"text","text":": "},{"kind":"typeIdentifier","text":"OrderSource","preciseIdentifier":"s:15DXFeedFramework11OrderSourceC"},{"kind":"text","text":"?"}],"type":"topic","url":"\/documentation\/dxfeedframework\/ordersource\/compsoitebid","abstract":[{"type":"text","text":"Bid side of a composite "},{"isActive":true,"identifier":"doc:\/\/com.dxfeed.DXFeedFramework\/documentation\/DXFeedFramework\/Quote","type":"reference"}],"role":"symbol","title":"compsoiteBid"},"doc://com.dxfeed.DXFeedFramework/documentation/DXFeedFramework/AnalyticOrder":{"kind":"symbol","identifier":"doc:\/\/com.dxfeed.DXFeedFramework\/documentation\/DXFeedFramework\/AnalyticOrder","fragments":[{"kind":"keyword","text":"class"},{"kind":"text","text":" "},{"text":"AnalyticOrder","kind":"identifier"}],"abstract":[{"type":"text","text":"Represents an extension of "},{"identifier":"doc:\/\/com.dxfeed.DXFeedFramework\/documentation\/DXFeedFramework\/Order","isActive":true,"type":"reference"},{"text":" introducing analytics information,","type":"text"},{"type":"text","text":" "},{"text":"e.g. adding to this order iceberg related information ","type":"text"},{"isActive":true,"type":"reference","identifier":"doc:\/\/com.dxfeed.DXFeedFramework\/documentation\/DXFeedFramework\/AnalyticOrder\/icebergPeakSize"},{"text":", ","type":"text"},{"identifier":"doc:\/\/com.dxfeed.DXFeedFramework\/documentation\/DXFeedFramework\/AnalyticOrder\/icebergHiddenSize","type":"reference","isActive":true},{"type":"text","text":", "},{"type":"reference","identifier":"doc:\/\/com.dxfeed.DXFeedFramework\/documentation\/DXFeedFramework\/AnalyticOrder\/icebergExecutedSize","isActive":true}],"url":"\/documentation\/dxfeedframework\/analyticorder","type":"topic","role":"symbol","title":"AnalyticOrder","navigatorTitle":[{"text":"AnalyticOrder","kind":"identifier"}]},"doc://com.dxfeed.DXFeedFramework/documentation/DXFeedFramework/OrderSource/BXTR":{"role":"symbol","kind":"symbol","abstract":[{"type":"text","text":"Bats Europe TRF."}],"identifier":"doc:\/\/com.dxfeed.DXFeedFramework\/documentation\/DXFeedFramework\/OrderSource\/BXTR","fragments":[{"kind":"keyword","text":"static"},{"kind":"text","text":" "},{"text":"let","kind":"keyword"},{"kind":"text","text":" "},{"kind":"identifier","text":"BXTR"},{"kind":"text","text":": "},{"preciseIdentifier":"s:15DXFeedFramework11OrderSourceC","kind":"typeIdentifier","text":"OrderSource"},{"text":"?","kind":"text"}],"type":"topic","url":"\/documentation\/dxfeedframework\/ordersource\/bxtr","title":"BXTR"},"doc://com.dxfeed.DXFeedFramework/documentation/DXFeedFramework/OrderSource/BYX":{"abstract":[{"type":"text","text":"Bats BYX Exchange."}],"role":"symbol","identifier":"doc:\/\/com.dxfeed.DXFeedFramework\/documentation\/DXFeedFramework\/OrderSource\/BYX","kind":"symbol","type":"topic","title":"BYX","url":"\/documentation\/dxfeedframework\/ordersource\/byx","fragments":[{"kind":"keyword","text":"static"},{"text":" ","kind":"text"},{"text":"let","kind":"keyword"},{"kind":"text","text":" "},{"text":"BYX","kind":"identifier"},{"text":": ","kind":"text"},{"preciseIdentifier":"s:15DXFeedFramework11OrderSourceC","kind":"typeIdentifier","text":"OrderSource"},{"text":"?","kind":"text"}]},"doc://com.dxfeed.DXFeedFramework/documentation/DXFeedFramework/OrderSource/XNFI":{"role":"symbol","fragments":[{"text":"static","kind":"keyword"},{"text":" ","kind":"text"},{"text":"let","kind":"keyword"},{"text":" ","kind":"text"},{"text":"XNFI","kind":"identifier"},{"text":": ","kind":"text"},{"kind":"typeIdentifier","text":"OrderSource","preciseIdentifier":"s:15DXFeedFramework11OrderSourceC"},{"kind":"text","text":"?"}],"type":"topic","identifier":"doc:\/\/com.dxfeed.DXFeedFramework\/documentation\/DXFeedFramework\/OrderSource\/XNFI","kind":"symbol","abstract":[{"type":"text","text":"NASDAQ Fixed Income."}],"url":"\/documentation\/dxfeedframework\/ordersource\/xnfi","title":"XNFI"},"doc://com.dxfeed.DXFeedFramework/documentation/DXFeedFramework/OrderSource/ISE":{"abstract":[{"text":"International Securities Exchange.","type":"text"}],"role":"symbol","type":"topic","fragments":[{"kind":"keyword","text":"static"},{"text":" ","kind":"text"},{"text":"let","kind":"keyword"},{"text":" ","kind":"text"},{"kind":"identifier","text":"ISE"},{"text":": ","kind":"text"},{"text":"OrderSource","preciseIdentifier":"s:15DXFeedFramework11OrderSourceC","kind":"typeIdentifier"},{"text":"?","kind":"text"}],"kind":"symbol","url":"\/documentation\/dxfeedframework\/ordersource\/ise","title":"ISE","identifier":"doc:\/\/com.dxfeed.DXFeedFramework\/documentation\/DXFeedFramework\/OrderSource\/ISE"},"doc://com.dxfeed.DXFeedFramework/documentation/DXFeedFramework/OrderSource/smfe-2a6vf":{"title":"smfe","abstract":[{"type":"text","text":"Small Exchange. Record for price level book."}],"identifier":"doc:\/\/com.dxfeed.DXFeedFramework\/documentation\/DXFeedFramework\/OrderSource\/smfe-2a6vf","url":"\/documentation\/dxfeedframework\/ordersource\/smfe-2a6vf","type":"topic","role":"symbol","fragments":[{"kind":"keyword","text":"static"},{"kind":"text","text":" "},{"text":"let","kind":"keyword"},{"kind":"text","text":" "},{"text":"smfe","kind":"identifier"},{"text":": ","kind":"text"},{"kind":"typeIdentifier","text":"OrderSource","preciseIdentifier":"s:15DXFeedFramework11OrderSourceC"},{"text":"?","kind":"text"}],"kind":"symbol"},"doc://com.dxfeed.DXFeedFramework/documentation/DXFeedFramework/OrderSource/DEA":{"title":"DEA","identifier":"doc:\/\/com.dxfeed.DXFeedFramework\/documentation\/DXFeedFramework\/OrderSource\/DEA","role":"symbol","type":"topic","abstract":[{"text":"Direct-Edge EDGA Exchange.","type":"text"}],"kind":"symbol","fragments":[{"text":"static","kind":"keyword"},{"text":" ","kind":"text"},{"text":"let","kind":"keyword"},{"kind":"text","text":" "},{"kind":"identifier","text":"DEA"},{"text":": ","kind":"text"},{"text":"OrderSource","kind":"typeIdentifier","preciseIdentifier":"s:15DXFeedFramework11OrderSourceC"},{"kind":"text","text":"?"}],"url":"\/documentation\/dxfeedframework\/ordersource\/dea"},"doc://com.dxfeed.DXFeedFramework/documentation/DXFeedFramework/OrderSource/valueOf(name:)":{"title":"valueOf(name:)","role":"symbol","kind":"symbol","url":"\/documentation\/dxfeedframework\/ordersource\/valueof(name:)","type":"topic","abstract":[{"text":"Returns order source for the specified source name.","type":"text"}],"identifier":"doc:\/\/com.dxfeed.DXFeedFramework\/documentation\/DXFeedFramework\/OrderSource\/valueOf(name:)","fragments":[{"kind":"keyword","text":"static"},{"kind":"text","text":" "},{"text":"func","kind":"keyword"},{"kind":"text","text":" "},{"kind":"identifier","text":"valueOf"},{"text":"(","kind":"text"},{"text":"name","kind":"externalParam"},{"text":": ","kind":"text"},{"text":"String","kind":"typeIdentifier","preciseIdentifier":"s:SS"},{"text":") ","kind":"text"},{"text":"throws","kind":"keyword"},{"text":" -> ","kind":"text"},{"preciseIdentifier":"s:15DXFeedFramework11OrderSourceC","text":"OrderSource","kind":"typeIdentifier"}]},"doc://com.dxfeed.DXFeedFramework/documentation/DXFeedFramework/OrderSource/publishable(eventType:)":{"title":"publishable(eventType:)","abstract":[{"type":"text","text":"Returns a list of publishable order sources for a given event type."}],"url":"\/documentation\/dxfeedframework\/ordersource\/publishable(eventtype:)","role":"symbol","type":"topic","kind":"symbol","identifier":"doc:\/\/com.dxfeed.DXFeedFramework\/documentation\/DXFeedFramework\/OrderSource\/publishable(eventType:)","fragments":[{"text":"static","kind":"keyword"},{"kind":"text","text":" "},{"text":"func","kind":"keyword"},{"text":" ","kind":"text"},{"text":"publishable","kind":"identifier"},{"kind":"text","text":"("},{"text":"eventType","kind":"externalParam"},{"text":": ","kind":"text"},{"kind":"typeIdentifier","text":"AnyClass","preciseIdentifier":"s:s8AnyClassa"},{"text":") ","kind":"text"},{"text":"throws","kind":"keyword"},{"text":" -> [","kind":"text"},{"kind":"typeIdentifier","preciseIdentifier":"s:15DXFeedFramework11OrderSourceC","text":"OrderSource"},{"text":"]","kind":"text"}]},"doc://com.dxfeed.DXFeedFramework/documentation/DXFeedFramework/OrderSource/ICE":{"title":"ICE","fragments":[{"text":"static","kind":"keyword"},{"kind":"text","text":" "},{"kind":"keyword","text":"let"},{"kind":"text","text":" "},{"text":"ICE","kind":"identifier"},{"kind":"text","text":": "},{"text":"OrderSource","kind":"typeIdentifier","preciseIdentifier":"s:15DXFeedFramework11OrderSourceC"},{"text":"?","kind":"text"}],"role":"symbol","identifier":"doc:\/\/com.dxfeed.DXFeedFramework\/documentation\/DXFeedFramework\/OrderSource\/ICE","type":"topic","kind":"symbol","abstract":[{"type":"text","text":"Intercontinental Exchange."}],"url":"\/documentation\/dxfeedframework\/ordersource\/ice"},"doc://com.dxfeed.DXFeedFramework/documentation/DXFeedFramework/OrderSource/dex-866to":{"role":"symbol","fragments":[{"text":"static","kind":"keyword"},{"text":" ","kind":"text"},{"text":"let","kind":"keyword"},{"text":" ","kind":"text"},{"text":"dex","kind":"identifier"},{"text":": ","kind":"text"},{"kind":"typeIdentifier","text":"OrderSource","preciseIdentifier":"s:15DXFeedFramework11OrderSourceC"},{"text":"?","kind":"text"}],"type":"topic","identifier":"doc:\/\/com.dxfeed.DXFeedFramework\/documentation\/DXFeedFramework\/OrderSource\/dex-866to","kind":"symbol","abstract":[{"text":"Direct-Edge EDGX Exchange. Record for price level book.","type":"text"}],"title":"dex","url":"\/documentation\/dxfeedframework\/ordersource\/dex-866to"},"doc://com.dxfeed.DXFeedFramework/documentation/DXFeedFramework/OrderSource/isFullOrderBook()":{"abstract":[{"text":"Gets a value indicating whether this source supports Full Order Book.","type":"text"}],"role":"symbol","identifier":"doc:\/\/com.dxfeed.DXFeedFramework\/documentation\/DXFeedFramework\/OrderSource\/isFullOrderBook()","fragments":[{"text":"func","kind":"keyword"},{"text":" ","kind":"text"},{"kind":"identifier","text":"isFullOrderBook"},{"kind":"text","text":"() -> "},{"kind":"typeIdentifier","preciseIdentifier":"s:Sb","text":"Bool"}],"title":"isFullOrderBook()","type":"topic","url":"\/documentation\/dxfeedframework\/ordersource\/isfullorderbook()","kind":"symbol"},"doc://com.dxfeed.DXFeedFramework/documentation/DXFeedFramework/OrderSource/DEX-8eswp":{"title":"DEX","identifier":"doc:\/\/com.dxfeed.DXFeedFramework\/documentation\/DXFeedFramework\/OrderSource\/DEX-8eswp","role":"symbol","type":"topic","abstract":[{"text":"Direct-Edge EDGX Exchange.","type":"text"}],"kind":"symbol","fragments":[{"text":"static","kind":"keyword"},{"text":" ","kind":"text"},{"text":"let","kind":"keyword"},{"kind":"text","text":" "},{"text":"DEX","kind":"identifier"},{"text":": ","kind":"text"},{"kind":"typeIdentifier","text":"OrderSource","preciseIdentifier":"s:15DXFeedFramework11OrderSourceC"},{"kind":"text","text":"?"}],"url":"\/documentation\/dxfeedframework\/ordersource\/dex-8eswp"}}}